ezoff/__init__.py
ezoff/_auth.py
ezoff/_helpers.py
ezoff/assets.py
ezoff/bundle.py
ezoff/checklists.py
ezoff/data_model.py
ezoff/enums.py
ezoff/exceptions.py
ezoff/ezo_cache.py
ezoff/groups.py
ezoff/inventory.py
ezoff/locations.py
ezoff/members.py
ezoff/members_v1.py
ezoff/packages.py
ezoff/projects.py
ezoff/purchase_orders.py
ezoff/retire_reasons.py
ezoff/stock_assets.py
ezoff/vendors.py
ezoff/work_orders.py
ezoff-1.24.9.dist-info/WHEEL
ezoff-1.24.9.dist-info/METADATA
ezoff-1.24.9.dist-info/RECORD
