Metadata-Version: 2.3
Name: ezoff
Version: 1.24.9
Summary: Python package for interacting with EZOffice API
Author: Jordan Maynor
Author-email: Jordan Maynor <jmaynor@pepsimidamerica.com>
License: This is free and unencumbered software released into the public domain.
Classifier: Programming Language :: Python :: 3
Classifier: License :: OSI Approved :: The Unlicense (Unlicense)
Classifier: Operating System :: OS Independent
Requires-Dist: pydantic>=2.11.9
Requires-Dist: requests>=2.32.5
Requires-Dist: tenacity>=9.1.2
Requires-Python: >=3.10
Project-URL: Homepage, https://github.com/pepsimidamerica/ezoff
